riotee_gateway/__init__.py
riotee_gateway/cli.py
riotee_gateway/client.py
riotee_gateway/packet_model.py
riotee_gateway/server.py
riotee_gateway/transceiver.py
riotee_gateway-0.1.1.dist-info/entry_points.txt
riotee_gateway-0.1.1.dist-info/LICENSE.txt
riotee_gateway-0.1.1.dist-info/WHEEL
riotee_gateway-0.1.1.dist-info/METADATA
riotee_gateway-0.1.1.dist-info/RECORD
